mypackage/__init__.py
mypackage/example.py
ramagopr_myproject-0.0.2.dist-info/LICENSE
ramagopr_myproject-0.0.2.dist-info/METADATA
ramagopr_myproject-0.0.2.dist-info/WHEEL
ramagopr_myproject-0.0.2.dist-info/top_level.txt
ramagopr_myproject-0.0.2.dist-info/RECORD
